funputer/__init__.py
funputer/analyzer.py
funputer/cli.py
funputer/exceptions.py
funputer/io.py
funputer/memory_utils.py
funputer/metadata_inference.py
funputer/models.py
funputer/outliers.py
funputer/preflight.py
funputer/proposal.py
funputer-1.7.1.dist-info/licenses/LICENSE
funputer-1.7.1.dist-info/METADATA
funputer-1.7.1.dist-info/WHEEL
funputer-1.7.1.dist-info/entry_points.txt
funputer-1.7.1.dist-info/top_level.txt
funputer-1.7.1.dist-info/RECORD
