Metadata-Version: 2.4
Name: funputer
Version: 1.7.1
Summary: Intelligent imputation analysis with automatic data validation, metadata inference, storage type detection, percentile-based ranges, and frequency-based categorical filtering
Author-email: Rajesh Ramachander <rajeshr.technocraft@gmail.com>
License-Expression: LicenseRef-Proprietary
Project-URL: Homepage, https://pypi.org/project/funputer/
Project-URL: Documentation, https://pypi.org/project/funputer/
Keywords: imputation,missing-data,data-science,machine-learning,pandas,auto-inference,metadata,preflight,validation,percentile,outlier-detection,ranges,categorical,frequency-filtering,statistical-significance,dtype-detection,storage-type
Classifier: Development Status :: 4 - Beta
Classifier: Intended Audience :: Developers
Classifier: Intended Audience :: Science/Research
Classifier: Programming Language :: Python :: 3
Classifier: Programming Language :: Python :: 3.9
Classifier: Programming Language :: Python :: 3.10
Classifier: Programming Language :: Python :: 3.11
Classifier: Programming Language :: Python :: 3.12
Classifier: Topic :: Scientific/Engineering
Classifier: Topic :: Software Development :: Libraries :: Python Modules
Requires-Python: >=3.9
License-File: LICENSE
Requires-Dist: pandas>=1.5.0
Requires-Dist: numpy>=1.21.0
Requires-Dist: scipy>=1.9.0
Requires-Dist: pyyaml>=6.0
Requires-Dist: click>=8.0.0
Requires-Dist: pydantic>=2.0.0
Requires-Dist: requests>=2.20.0
Requires-Dist: jsonschema>=4.0.0
Provides-Extra: dev
Requires-Dist: pytest>=7.0.0; extra == "dev"
Requires-Dist: pytest-cov>=4.0.0; extra == "dev"
Requires-Dist: black>=22.0.0; extra == "dev"
Requires-Dist: isort>=5.10.0; extra == "dev"
Requires-Dist: mypy>=1.0.0; extra == "dev"
Requires-Dist: flake8>=5.0.0; extra == "dev"
Dynamic: license-file
